{"openapi":"3.0.0","paths":{"/":{"get":{"operationId":"AppController_getHello","parameters":[],"responses":{"200":{"description":""}}}},"/users/me":{"get":{"operationId":"UsersController_getMe","parameters":[],"responses":{"200":{"description":""}},"tags":["users"],"security":[{"bearer":[]}]}}},"info":{"title":"Memorang AI Study API","description":"The Memorang AI Study API description","version":"1.0","contact":{}},"tags":[],"servers":[],"components":{"securitySchemes":{"bearer":{"scheme":"bearer","bearerFormat":"JWT","type":"http"}},"schemas":{}}}